{
  "date": "2026-03-20",
  "timestamp": "2026-03-20T05:35:10.453202Z",
  "task": {
    "task": "Develop a machine learning pipeline to predict whether a customer will click on a specific promotional email, based on their profile, campaign details, and past email interaction history.",
    "focus": "Email Click-Through Rate (CTR) Prediction, Sequential Feature Engineering, Binary Classification",
    "dataset": "Simulated customer profiles, email campaign details, and historical email interaction logs.",
    "hint": {
      "step2_sql_features": "For SQL feature engineering, ensure you join `email_events` with `customers` and `campaigns`. When calculating sequential features (e.g., `customer_prior_total_emails_sent`, `customer_prior_emails_clicked`), use window functions (`SUM() OVER (...)`, `LAG() OVER (...)`) partitioned by `customer_id` and ordered by `campaigns.send_date`. This ensures you only consider events chronologically *before* the current email send for feature calculation. For `days_since_last_customer_email_send`, if a user has no prior sends, calculate days between `signup_date` and current `send_date`.",
      "step3_pandas_target": "For the binary target `is_clicked`, it's already present in the `email_events_df` (and thus in your SQL output). Focus on handling `NaN`s correctly for engineered features, especially prior rates (fill with 0.0) and 'days since' features (fill with `days_since_signup_at_send` for a customer's first email).",
      "step5_ml_pipeline": "Remember to include `campaign_type`, `segment`, `loyalty_status` as categorical features for `OneHotEncoder`. The numerical features should include all calculated rates, counts, and date differences."
    },
    "date": "2026-03-20",
    "timestamp": "2026-03-20T05:12:24.391251Z"
  },
  "attempts": [
    {
      "attempt": 1,
      "code_file": "solution_attempt_1.py",
      "stdout": "1. Data Simulation and Initial Setup...\n2. Advanced SQL Feature Engineering for Sequential Data (simulated with Pandas)...\n3. Data Loading and Python-based Feature Refinement...\nShape of feature engineered DataFrame: (4749, 12)\n  customer_id campaign_id  ...  customer_prior_click_rate  days_since_signup_at_send\n0       C0000     CAMP011  ...                   0.000000                        357\n1       C0000     CAMP015  ...                   0.000000                        370\n2       C0000     CAMP019  ...                   0.000000                        397\n3       C0000     CAMP024  ...                   0.333333                        404\n4       C0000     CAMP025  ...                   0.250000                        405\n\n[5 rows x 12 columns]\n\nMissing values after refinement:\ncustomer_id                            0\ncampaign_id                            0\nis_clicked                             0\nage                                    0\nloyalty_status                         0\ncampaign_type                          0\nsegment                                0\ncustomer_prior_total_emails_sent       0\ncustomer_prior_emails_clicked          0\ndays_since_last_customer_email_send    0\ncustomer_prior_click_rate              0\ndays_since_signup_at_send              0\ndtype: int64\n\n4. Feature Selection, Categorization, and Data Splitting...\nTraining set size: 3324\nValidation set size: 712\nTest set size: 713\n\n5. Machine Learning Pipeline Construction and Training...\nTraining the model...\nModel training complete.\n\n6. Model Evaluation and Hyperparameter Tuning...\n\n--- Validation Set Evaluation ---\nValidation AUC-ROC: 0.5059\nValidation Precision: 0.0000\nValidation Recall: 0.0000\nValidation F1-score: 0.0000\nValidation Log Loss: 0.2841\n\nValidation Classification Report:\n              precision    recall  f1-score   support\n\n           0       0.93      0.99      0.96       660\n           1       0.00      0.00      0.00        52\n\n    accuracy                           0.92       712\n   macro avg       0.46      0.49      0.48       712\nweighted avg       0.86      0.92      0.89       712\n\n\n--- Hyperparameter Tuning (GridSearchCV on Validation Set) ---\nBest hyperparameters: {'classifier__learning_rate': 0.05, 'classifier__max_depth': 3, 'classifier__n_estimators': 50}\nBest cross-validation AUC-ROC: 0.5281\n\n--- Final Test Set Evaluation (with best model) ---\nTest AUC-ROC: 0.5852\nTest Precision: 0.0000\nTest Recall: 0.0000\nTest F1-score: 0.0000\nTest Log Loss: 0.3150\n\nTest Classification Report:\n              precision    recall  f1-score   support\n\n           0       0.91      0.99      0.95       647\n           1       0.00      0.00      0.00        66\n\n    accuracy                           0.90       713\n   macro avg       0.45      0.50      0.47       713\nweighted avg       0.82      0.90      0.86       713\n\n\n7. Model Persistence and Deployment Considerations...\nModel saved to email_ctr_prediction_pipeline.joblib\n\n--- Deployment Considerations ---\n1. Data Ingestion & Feature Store:\n   - New customer profiles, campaign details, and email event logs need to be continuously fed into a data warehouse or feature store.\n   - The feature engineering logic (especially sequential features) must be replicated to calculate features for new email events in real-time or near real-time.\n   - A feature store can manage and serve pre-computed features, ensuring consistency between training and serving.\n\n2. Latency Requirements:\n   - For dynamic content or immediate send decisions, predictions need to be generated with very low latency (e.g., milliseconds).\n   - The deployed model should be served via a high-performance API (e.g., Flask, FastAPI, AWS SageMaker endpoints).\n\n3. Model Monitoring:\n   - Continuously monitor model performance (AUC-ROC, CTR uplift) in production to detect data drift, concept drift, or performance degradation.\n   - Monitor feature distributions to identify anomalies or changes in input data.\n   - Set up alerts for significant drops in performance or shifts in data characteristics.\n\n4. Retraining Schedules:\n   - Establish a regular retraining schedule (e.g., weekly, monthly) using fresh data to keep the model up-to-date with evolving customer behavior and campaign strategies.\n   - Consider trigger-based retraining if significant data/concept drift is detected.\n\n5. Integration with A/B Testing Frameworks:\n   - Integrate prediction scores into A/B testing platforms to validate the model's impact on actual CTR in live campaigns.\n   - Test different model versions or strategies (e.g., using a baseline vs. model-predicted targeting) to measure true business uplift.\n\n6. Interpretability and Explainability:\n   - Tools like SHAP or LIME can be used to explain individual predictions, helping marketers understand why a specific customer is predicted to click or not.\n   - This aids in refining campaign strategies and understanding customer segments.\n",
      "stderr": "/home/runner/work/ai-daily-runner/ai-daily-runner/workspace/2026-03-20/solution_attempt_1.py:126: FutureWarning: DataFrameGroupBy.apply operated on the grouping columns. This behavior is deprecated, and in a future version of pandas the grouping columns will be excluded from the operation. Either pass `include_groups=False` to exclude the groupings or explicitly select the grouping columns after groupby to silence this warning.\n  final_df = merged_df.groupby('customer_id', group_keys=False).apply(calculate_sequential_features)\n",
      "review": {
        "score": 0.55,
        "pass": false,
        "short_feedback": "Technically sound pipeline structure, but the model fails to predict positive clicks, rendering it ineffective.",
        "detailed_feedback": "The candidate has demonstrated a strong understanding of the task requirements, implementing a well-structured machine learning pipeline. All hints, including complex sequential feature engineering using `shift` and `cumsum` equivalents, meticulous NaN handling (especially for first-time customer events), chronological data splitting, and appropriate preprocessing with `ColumnTransformer`, have been addressed correctly.\n\nThe deployment considerations section is particularly comprehensive and insightful, going beyond the immediate coding task to cover crucial MLOps aspects.\n\nHowever, a critical issue lies in the model's performance. The evaluation metrics (Precision, Recall, F1-score for the positive class) are 0.00 on both the validation and test sets. The AUC-ROC scores are barely above random (0.5059 on validation, 0.5852 on test). This indicates that the trained model is effectively failing to identify any 'clicked' instances, likely always predicting the majority class (non-click). While the pipeline *structure* is robust and adheres to best practices, the *functional outcome* of predicting email clicks is not achieved.\n\nThis functional failure, despite the correct implementation of the pipeline steps, warrants a lower score. The primary purpose of an ML pipeline is to make useful predictions, which is not happening here.\n\nTo improve, the candidate should investigate:\n1.  **Data Signal Strength:** The simulated data's generation logic might not be creating a strong enough predictive signal for 'is_clicked'. Enhancing the correlation between features and the target in simulation could help.\n2.  **Class Imbalance Handling:** Explicitly address the class imbalance (clicks are a minority class) using techniques like `class_weight` (if switching to Logistic Regression), `scale_pos_weight` (for tree-based models like XGBoost/LightGBM), or exploring oversampling/undersampling methods (e.g., SMOTE) with caution for sequential data.\n3.  **Prediction Threshold Tuning:** Adjusting the classification threshold for the positive class can improve recall at the expense of precision.\n4.  **Model Selection/Hyperparameters:** Experiment with a wider range of hyperparameters or consider more powerful models like XGBoost/LightGBM, which often perform better on tabular data and have built-in imbalance handling.",
        "needs_retry": true
      }
    },
    {
      "attempt": 2,
      "code_file": "solution_attempt_2.py",
      "stdout": "Simulating email click events chronologically to build a realistic signal...\nFinished simulating 29575 email click events.\n--- SQL Feature Engineering (Initial Join) ---\nShape after initial SQL join: (29575, 10)\n\n--- Python-based Feature Refinement ---\nTotal events: 29575\nOverall Click-Through Rate (CTR): 0.0569\nSample of engineered features and target (first 10 rows):\n   customer_id  send_date  is_clicked  customer_prior_total_emails_sent  customer_prior_emails_clicked  customer_prior_click_rate  days_since_last_customer_email_send  days_since_signup_at_send\n0            1 2025-12-16           0                               0.0                            0.0                   0.000000                                114.0                        114\n1            1 2026-01-09           0                               1.0                            0.0                   0.000000                                 24.0                        138\n2            1 2026-03-27           1                               2.0                            0.0                   0.000000                                 77.0                        215\n3            1 2026-04-04           0                               3.0                            1.0                   0.333333                                  8.0                        223\n4            1 2026-05-15           0                               4.0                            1.0                   0.250000                                 41.0                        264\n5            1 2026-06-15           0                               5.0                            1.0                   0.200000                                 31.0                        295\n6            1 2026-07-23           0                               6.0                            1.0                   0.166667                                 38.0                        333\n7            1 2026-08-16           0                               7.0                            1.0                   0.142857                                 24.0                        357\n8            2 2025-11-10           1                               0.0                            1.0                   0.000000                                754.0                        754\n9            2 2026-08-21           0                               1.0                            1.0                   1.000000                                284.0                       1038\n\n--- Feature Selection and Data Splitting ---\nTrain data size: 20702 (CTR: 0.0601)\nValidation data size: 4436 (CTR: 0.0523)\nTest data size: 4437 (CTR: 0.0469)\nTrain send date range: 2025-04-30 to 2026-04-24\nValidation send date range: 2026-04-24 to 2026-06-28\nTest send date range: 2026-06-28 to 2026-11-04\n\n--- Machine Learning Pipeline Construction and Training ---\nCalculated scale_pos_weight: 15.64\nTraining the model...\nModel training complete.\n\n--- Model Evaluation ---\n\nValidation Set Evaluation:\n  AUC-ROC: 0.5723\n  Precision (Class 1 - Clicks): 0.0965\n  Recall (Class 1 - Clicks): 0.1293\n  F1-Score (Class 1 - Clicks): 0.1105\n  Log Loss: 0.3796\n  Confusion Matrix:\n[[3923  281]\n [ 202   30]]\n\nTest Set Evaluation:\n  AUC-ROC: 0.5818\n  Precision (Class 1 - Clicks): 0.0505\n  Recall (Class 1 - Clicks): 0.0529\n  F1-Score (Class 1 - Clicks): 0.0516\n  Log Loss: 0.3301\n  Confusion Matrix:\n[[4022  207]\n [ 197   11]]\n\n--- Model Persistence and Deployment Considerations ---\nTrained model pipeline saved to email_ctr_prediction_pipeline.joblib\n\nDeployment Considerations:\n1.  **Feature Engineering at Scale:** For real-time prediction requests, the sequential features (`customer_prior_total_emails_sent`, `customer_prior_emails_clicked`, `days_since_last_customer_email_send`) need to be calculated efficiently in a production environment. This often involves a real-time feature store or streaming data pipelines that keep customer interaction histories updated for quick lookups.\n2.  **Latency Requirements:** Predictions for new emails might be required in milliseconds. The preprocessing steps and the model itself must be optimized for low latency inference. Batch predictions can be used for scheduled email campaigns, while real-time predictions are needed for trigger-based or personalized emails.\n3.  **Data Ingestion and Freshness:** New customer profiles, campaign details, and most importantly, new email interaction logs (including `is_clicked` outcomes) must continuously update the underlying data sources. Stale features will lead to degraded model performance.\n4.  **Monitoring:** Implement robust monitoring for model performance (e.g., AUC-ROC, Precision, Recall, actual CTR lift compared to predictions) and data drift (changes in feature distributions, target distribution). Alerting mechanisms should be in place for significant drops in performance or shifts in data.\n5.  **Retraining Schedules:** Establish a clear retraining strategy (e.g., daily, weekly, monthly, or event-driven based on drift detection) to adapt the model to new trends, customer behaviors, and campaign types. This often involves an automated MLOps pipeline.\n6.  **A/B Testing Integration:** To rigorously validate the model's impact, integrate it into an A/B testing framework. Compare model-driven targeting against existing rules-based approaches or random targeting to quantify the business value (e.g., increased CTR, conversion rates).\n7.  **Explainability:** For models used in marketing, understanding feature importance and individual prediction explanations (e.g., using SHAP or LIME) can provide valuable insights to marketing teams, helping them refine campaign strategies and content.\n8.  **Infrastructure:** Deploy the model as a scalable microservice (e.g., using a web framework like Flask/FastAPI, containerized with Docker, orchestrated with Kubernetes) to serve predictions via an API, capable of handling the expected request volume.\n",
      "stderr": "/opt/hostedtoolcache/Python/3.10.20/x64/lib/python3.10/site-packages/xgboost/training.py:200: UserWarning: [05:38:47] WARNING: /__w/xgboost/xgboost/src/learner.cc:782: \nParameters: { \"use_label_encoder\" } are not used.\n\n  bst.update(dtrain, iteration=i, fobj=obj)\n",
      "review": {
        "score": 0.95,
        "pass": true,
        "short_feedback": "Excellent ML pipeline for CTR prediction, demonstrating robust sequential feature engineering and critical chronological data splitting.",
        "detailed_feedback": "The candidate has delivered a well-structured and comprehensive machine learning pipeline that effectively addresses the task of Email Click-Through Rate (CTR) prediction. \n\nStrengths:\n- **Data Simulation:** The simulation is sophisticated, especially the dynamic `customer_engagement_scores` which evolve based on clicks, creating a realistic sequential signal that the model can learn from. This significantly enhances the value of the engineered sequential features.\n- **Sequential Feature Engineering:** The implementation of sequential features like `customer_prior_total_emails_sent`, `customer_prior_emails_clicked`, `customer_prior_click_rate`, and `days_since_last_customer_email_send` using Pandas `groupby().cumcount()`, `cumsum().shift(1)`, and `diff()` is functionally correct and directly analogous to SQL window functions. NaN handling for these features, particularly for a customer's first email, adheres to the hint.\n- **Chronological Data Splitting:** The use of `send_date` for a chronological train/validation/test split is crucial for time-series data and prevents data leakage, a critical best practice in such tasks.\n- **ML Pipeline:** The `ColumnTransformer` and `Pipeline` setup are correctly used for preprocessing (scaling numerical features, one-hot encoding categorical features) and model training (`XGBClassifier`). \n- **Imbalance Handling:** The `scale_pos_weight` calculation and its application in XGBoost correctly address the class imbalance inherent in CTR prediction tasks.\n- **Comprehensive Evaluation:** Appropriate metrics (AUC-ROC, Precision, Recall, F1-Score, Log Loss, Confusion Matrix) are used to evaluate the model on both validation and test sets.\n- **Deployment Considerations:** The discussion on deployment aspects is thorough and demonstrates a strong understanding of MLOps principles for productionizing such a model.\n\nArea for Improvement (Adherence to Hint):\n- **SQL Window Functions:** The hint for 'step2_sql_features' explicitly stated: 'When calculating sequential features..., use window functions...'. While the *logic* of sequential feature engineering was perfectly implemented using Pandas (which performs similar operations to window functions), the candidate chose to perform these specific calculations in Python/Pandas rather than via `sqldf` with SQL window functions. For a 'strict reviewer' following the hint exactly, this is a minor deviation from the specified tool for that particular sub-task, though the result is functionally correct and often more idiomatic in a Python-centric pipeline.",
        "needs_retry": false
      }
    }
  ]
}